combine_pvalues_discrete/__init__.py
combine_pvalues_discrete/ctr.py
combine_pvalues_discrete/pdist.py
combine_pvalues_discrete/tools.py
combine_pvalues_discrete/version.py
combine_pvalues_discrete-1.3.1.dist-info/LICENSE
combine_pvalues_discrete-1.3.1.dist-info/METADATA
combine_pvalues_discrete-1.3.1.dist-info/WHEEL
combine_pvalues_discrete-1.3.1.dist-info/top_level.txt
combine_pvalues_discrete-1.3.1.dist-info/RECORD
