Metadata-Version: 2.2
Name: combine_pvalues_discrete
Version: 1.3.1
Summary: A Python toolbox for combining p values from tests with a discrete statistics
Author-email: Gerrit Ansmann <gansmann@uni-koeln.de>
License: BSD-3-Clause
Project-URL: Documentation, https://combine-p-values-discrete.readthedocs.io
Project-URL: Homepage, https://github.com/BPSB/combine-p-values-discrete
Classifier: License :: OSI Approved :: BSD License
Classifier: Operating System :: POSIX
Classifier: Operating System :: MacOS :: MacOS X
Classifier: Operating System :: Microsoft :: Windows
Classifier: Programming Language :: Python
Classifier: Topic :: Scientific/Engineering
Requires-Python: >=3.7
License-File: LICENSE
Requires-Dist: numpy
Requires-Dist: scipy>=1.14
Provides-Extra: test
Requires-Dist: symengine; extra == "test"
Requires-Dist: pytest-runner; extra == "test"
Requires-Dist: pytest-rng; extra == "test"
Requires-Dist: statsmodels; extra == "test"
